{
  "timestamp": "2026-01-15T15:32:02+01:00",
  "nodes": [
    {
      "name": "clab-nebula-serf4",
      "addr": "10.0.1.13",
      "port": 7946,
      "status": "alive",
      "tags": {},
      "coordinate": {
        "Vec": [
          0.006,
          0.0,
          0.0,
          0.0,
          0.0
        ],
        "Error": 0.0,
        "Adjustment": 0.0,
        "Height": 0.0
      },
      "rtts": {
        "clab-nebula-serf16": 8.66,
        "clab-nebula-serf19": 14.309,
        "clab-nebula-serf27": 17.436,
        "clab-nebula-serf30": 17.776,
        "clab-nebula-serf1": 6.0,
        "clab-nebula-serf6": 4.0,
        "clab-nebula-serf2": 4.0,
        "clab-nebula-serf10": 4.33,
        "clab-nebula-serf12": 5.895,
        "clab-nebula-serf15": 8.888,
        "clab-nebula-serf24": 13.592,
        "clab-nebula-serf21": 13.143,
        "clab-nebula-serf23": 13.143,
        "clab-nebula-serf29": 17.436,
        "clab-nebula-serf8": 5.895,
        "clab-nebula-serf14": 9.539,
        "clab-nebula-serf17": 8.888,
        "clab-nebula-serf28": 17.321,
        "clab-nebula-serf9": 4.77,
        "clab-nebula-serf11": 4.77,
        "clab-nebula-serf5": 2.0,
        "clab-nebula-serf18": 9.539,
        "clab-nebula-serf20": 13.592,
        "clab-nebula-serf25": 18.33,
        "clab-nebula-serf26": 17.776,
        "clab-nebula-serf3": 2.0,
        "clab-nebula-serf7": 7.399,
        "clab-nebula-serf13": 10.536,
        "clab-nebula-serf22": 12.99
      }
    },
    {
      "name": "clab-nebula-serf16",
      "addr": "10.0.2.15",
      "port": 7946,
      "status": "alive",
      "tags": {},
      "coordinate": {
        "Vec": [
          0.006,
          0.0086602540378,
          0.0,
          0.0,
          0.0
        ],
        "Error": 0.0,
        "Adjustment": 0.0,
        "Height": 0.0
      },
      "rtts": {
        "clab-nebula-serf4": 8.66,
        "clab-nebula-serf19": 7.399,
        "clab-nebula-serf27": 8.888,
        "clab-nebula-serf30": 9.539,
        "clab-nebula-serf1": 10.536,
        "clab-nebula-serf6": 9.539,
        "clab-nebula-serf2": 9.539,
        "clab-nebula-serf10": 4.33,
        "clab-nebula-serf12": 5.895,
        "clab-nebula-serf15": 2.0,
        "clab-nebula-serf24": 5.895,
        "clab-nebula-serf21": 4.77,
        "clab-nebula-serf23": 4.77,
        "clab-nebula-serf29": 8.888,
        "clab-nebula-serf8": 5.895,
        "clab-nebula-serf14": 4.0,
        "clab-nebula-serf17": 2.0,
        "clab-nebula-serf28": 8.66,
        "clab-nebula-serf9": 4.77,
        "clab-nebula-serf11": 4.77,
        "clab-nebula-serf5": 8.888,
        "clab-nebula-serf18": 4.0,
        "clab-nebula-serf20": 5.895,
        "clab-nebula-serf25": 10.536,
        "clab-nebula-serf26": 9.539,
        "clab-nebula-serf3": 8.888,
        "clab-nebula-serf7": 7.399,
        "clab-nebula-serf13": 6.0,
        "clab-nebula-serf22": 4.33
      }
    },
    {
      "name": "clab-nebula-serf19",
      "addr": "10.0.2.18",
      "port": 7946,
      "status": "alive",
      "tags": {},
      "coordinate": {
        "Vec": [
          0.0,
          0.012990381056700001,
          0.0,
          0.0,
          0.0
        ],
        "Error": 0.0,
        "Adjustment": 0.0,
        "Height": 0.0
      },
      "rtts": {
        "clab-nebula-serf4": 14.309,
        "clab-nebula-serf16": 7.399,
        "clab-nebula-serf27": 5.895,
        "clab-nebula-serf30": 10.897,
        "clab-nebula-serf1": 12.99,
        "clab-nebula-serf6": 16.394,
        "clab-nebula-serf2": 13.143,
        "clab-nebula-serf10": 10.536,
        "clab-nebula-serf12": 13.229,
        "clab-nebula-serf15": 5.895,
        "clab-nebula-serf24": 10.0,
        "clab-nebula-serf21": 4.0,
        "clab-nebula-serf23": 8.0,
        "clab-nebula-serf29": 9.097,
        "clab-nebula-serf8": 8.888,
        "clab-nebula-serf14": 4.77,
        "clab-nebula-serf17": 9.097,
        "clab-nebula-serf28": 7.399,
        "clab-nebula-serf9": 9.539,
        "clab-nebula-serf11": 11.79,
        "clab-nebula-serf5": 15.256,
        "clab-nebula-serf18": 10.897,
        "clab-nebula-serf20": 2.0,
        "clab-nebula-serf25": 4.33,
        "clab-nebula-serf26": 4.77,
        "clab-nebula-serf3": 13.592,
        "clab-nebula-serf7": 8.66,
        "clab-nebula-serf13": 4.33,
        "clab-nebula-serf22": 6.0
      }
    },
    {
      "name": "clab-nebula-serf27",
      "addr": "10.0.3.16",
      "port": 7946,
      "status": "alive",
      "tags": {},
      "coordinate": {
        "Vec": [
          0.004,
          0.0173205080756,
          0.0,
          0.0,
          0.0
        ],
        "Error": 0.0,
        "Adjustment": 0.0,
        "Height": 0.0
      },
      "rtts": {
        "clab-nebula-serf4": 17.436,
        "clab-nebula-serf16": 8.888,
        "clab-nebula-serf19": 5.895,
        "clab-nebula-serf30": 6.0,
        "clab-nebula-serf1": 17.776,
        "clab-nebula-serf6": 18.33,
        "clab-nebula-serf2": 17.436,
        "clab-nebula-serf10": 13.143,
        "clab-nebula-serf12": 14.309,
        "clab-nebula-serf15": 8.66,
        "clab-nebula-serf24": 7.399,
        "clab-nebula-serf21": 4.33,
        "clab-nebula-serf23": 5.895,
        "clab-nebula-serf29": 4.0,
        "clab-nebula-serf8": 13.143,
        "clab-nebula-serf14": 8.888,
        "clab-nebula-serf17": 9.539,
        "clab-nebula-serf28": 2.0,
        "clab-nebula-serf9": 12.99,
        "clab-nebula-serf11": 13.592,
        "clab-nebula-serf5": 17.776,
        "clab-nebula-serf18": 10.536,
        "clab-nebula-serf20": 4.77,
        "clab-nebula-serf25": 4.0,
        "clab-nebula-serf26": 2.0,
        "clab-nebula-serf3": 17.321,
        "clab-nebula-serf7": 13.592,
        "clab-nebula-serf13": 9.539,
        "clab-nebula-serf22": 4.77
      }
    },
    {
      "name": "clab-nebula-serf30",
      "addr": "10.0.3.19",
      "port": 7946,
      "status": "alive",
      "tags": {},
      "coordinate": {
        "Vec": [
          0.01,
          0.0173205080756,
          0.0,
          0.0,
          0.0
        ],
        "Error": 0.0,
        "Adjustment": 0.0,
        "Height": 0.0
      },
      "rtts": {
        "clab-nebula-serf4": 17.776,
        "clab-nebula-serf16": 9.539,
        "clab-nebula-serf19": 10.897,
        "clab-nebula-serf27": 6.0,
        "clab-nebula-serf1": 20.0,
        "clab-nebula-serf6": 17.321,
        "clab-nebula-serf2": 19.079,
        "clab-nebula-serf10": 13.592,
        "clab-nebula-serf12": 12.99,
        "clab-nebula-serf15": 10.536,
        "clab-nebula-serf24": 4.33,
        "clab-nebula-serf21": 7.399,
        "clab-nebula-serf23": 4.77,
        "clab-nebula-serf29": 2.0,
        "clab-nebula-serf8": 15.256,
        "clab-nebula-serf14": 11.79,
        "clab-nebula-serf17": 8.888,
        "clab-nebula-serf28": 4.0,
        "clab-nebula-serf9": 14.309,
        "clab-nebula-serf11": 13.143,
        "clab-nebula-serf5": 17.436,
        "clab-nebula-serf18": 8.66,
        "clab-nebula-serf20": 9.097,
        "clab-nebula-serf25": 10.0,
        "clab-nebula-serf26": 8.0,
        "clab-nebula-serf3": 18.33,
        "clab-nebula-serf7": 16.394,
        "clab-nebula-serf13": 13.229,
        "clab-nebula-serf22": 5.895
      }
    },
    {
      "name": "clab-nebula-serf1",
      "addr": "10.0.1.10",
      "port": 7946,
      "status": "alive",
      "tags": {},
      "coordinate": {
        "Vec": [
          0.0,
          0.0,
          0.0,
          0.0,
          0.0
        ],
        "Error": 0.0,
        "Adjustment": 0.0,
        "Height": 0.0
      },
      "rtts": {
        "clab-nebula-serf4": 6.0,
        "clab-nebula-serf16": 10.536,
        "clab-nebula-serf19": 12.99,
        "clab-nebula-serf27": 17.776,
        "clab-nebula-serf30": 20.0,
        "clab-nebula-serf6": 10.0,
        "clab-nebula-serf2": 2.0,
        "clab-nebula-serf10": 7.399,
        "clab-nebula-serf12": 10.897,
        "clab-nebula-serf15": 9.539,
        "clab-nebula-serf24": 16.394,
        "clab-nebula-serf21": 13.592,
        "clab-nebula-serf23": 15.256,
        "clab-nebula-serf29": 19.079,
        "clab-nebula-serf8": 4.77,
        "clab-nebula-serf14": 8.888,
        "clab-nebula-serf17": 11.79,
        "clab-nebula-serf28": 18.33,
        "clab-nebula-serf9": 5.895,
        "clab-nebula-serf11": 9.097,
        "clab-nebula-serf5": 8.0,
        "clab-nebula-serf18": 13.229,
        "clab-nebula-serf20": 13.143,
        "clab-nebula-serf25": 17.321,
        "clab-nebula-serf26": 17.436,
        "clab-nebula-serf3": 4.0,
        "clab-nebula-serf7": 4.33,
        "clab-nebula-serf13": 8.66,
        "clab-nebula-serf22": 14.309
      }
    },
    {
      "name": "clab-nebula-serf6",
      "addr": "10.0.1.15",
      "port": 7946,
      "status": "alive",
      "tags": {},
      "coordinate": {
        "Vec": [
          0.01,
          0.0,
          0.0,
          0.0,
          0.0
        ],
        "Error": 0.0,
        "Adjustment": 0.0,
        "Height": 0.0
      },
      "rtts": {
        "clab-nebula-serf4": 4.0,
        "clab-nebula-serf16": 9.539,
        "clab-nebula-serf19": 16.394,
        "clab-nebula-serf27": 18.33,
        "clab-nebula-serf30": 17.321,
        "clab-nebula-serf1": 10.0,
        "clab-nebula-serf2": 8.0,
        "clab-nebula-serf10": 5.895,
        "clab-nebula-serf12": 4.33,
        "clab-nebula-serf15": 10.536,
        "clab-nebula-serf24": 12.99,
        "clab-nebula-serf21": 14.309,
        "clab-nebula-serf23": 13.143,
        "clab-nebula-serf29": 17.436,
        "clab-nebula-serf8": 9.097,
        "clab-nebula-serf14": 11.79,
        "clab-nebula-serf17": 8.888,
        "clab-nebula-serf28": 17.776,
        "clab-nebula-serf9": 7.399,
        "clab-nebula-serf11": 4.77,
        "clab-nebula-serf5": 2.0,
        "clab-nebula-serf18": 8.66,
        "clab-nebula-serf20": 15.256,
        "clab-nebula-serf25": 20.0,
        "clab-nebula-serf26": 19.079,
        "clab-nebula-serf3": 6.0,
        "clab-nebula-serf7": 10.897,
        "clab-nebula-serf13": 13.229,
        "clab-nebula-serf22": 13.592
      }
    },
    {
      "name": "clab-nebula-serf2",
      "addr": "10.0.1.11",
      "port": 7946,
      "status": "alive",
      "tags": {},
      "coordinate": {
        "Vec": [
          0.002,
          0.0,
          0.0,
          0.0,
          0.0
        ],
        "Error": 0.0,
        "Adjustment": 0.0,
        "Height": 0.0
      },
      "rtts": {
        "clab-nebula-serf4": 4.0,
        "clab-nebula-serf16": 9.539,
        "clab-nebula-serf19": 13.143,
        "clab-nebula-serf27": 17.436,
        "clab-nebula-serf30": 19.079,
        "clab-nebula-serf1": 2.0,
        "clab-nebula-serf6": 8.0,
        "clab-nebula-serf10": 5.895,
        "clab-nebula-serf12": 9.097,
        "clab-nebula-serf15": 8.888,
        "clab-nebula-serf24": 15.256,
        "clab-nebula-serf21": 13.143,
        "clab-nebula-serf23": 14.309,
        "clab-nebula-serf29": 18.33,
        "clab-nebula-serf8": 4.33,
        "clab-nebula-serf14": 8.66,
        "clab-nebula-serf17": 10.536,
        "clab-nebula-serf28": 17.776,
        "clab-nebula-serf9": 4.77,
        "clab-nebula-serf11": 7.399,
        "clab-nebula-serf5": 6.0,
        "clab-nebula-serf18": 11.79,
        "clab-nebula-serf20": 12.99,
        "clab-nebula-serf25": 17.436,
        "clab-nebula-serf26": 17.321,
        "clab-nebula-serf3": 2.0,
        "clab-nebula-serf7": 4.77,
        "clab-nebula-serf13": 8.888,
        "clab-nebula-serf22": 13.592
      }
    },
    {
      "name": "clab-nebula-serf10",
      "addr": "10.0.1.19",
      "port": 7946,
      "status": "alive",
      "tags": {},
      "coordinate": {
        "Vec": [
          0.006,
          0.0043301270189,
          0.0,
          0.0,
          0.0
        ],
        "Error": 0.0,
        "Adjustment": 0.0,
        "Height": 0.0
      },
      "rtts": {
        "clab-nebula-serf4": 4.33,
        "clab-nebula-serf16": 4.33,
        "clab-nebula-serf19": 10.536,
        "clab-nebula-serf27": 13.143,
        "clab-nebula-serf30": 13.592,
        "clab-nebula-serf1": 7.399,
        "clab-nebula-serf6": 5.895,
        "clab-nebula-serf2": 5.895,
        "clab-nebula-serf12": 4.0,
        "clab-nebula-serf15": 4.77,
        "clab-nebula-serf24": 9.539,
        "clab-nebula-serf21": 8.888,
        "clab-nebula-serf23": 8.888,
        "clab-nebula-serf29": 13.143,
        "clab-nebula-serf8": 4.0,
        "clab-nebula-serf14": 5.895,
        "clab-nebula-serf17": 4.77,
        "clab-nebula-serf28": 12.99,
        "clab-nebula-serf9": 2.0,
        "clab-nebula-serf11": 2.0,
        "clab-nebula-serf5": 4.77,
        "clab-nebula-serf18": 5.895,
        "clab-nebula-serf20": 9.539,
        "clab-nebula-serf25": 14.309,
        "clab-nebula-serf26": 13.592,
        "clab-nebula-serf3": 4.77,
        "clab-nebula-serf7": 6.0,
        "clab-nebula-serf13": 7.399,
        "clab-nebula-serf22": 8.66
      }
    },
    {
      "name": "clab-nebula-serf12",
      "addr": "10.0.2.11",
      "port": 7946,
      "status": "alive",
      "tags": {},
      "coordinate": {
        "Vec": [
          0.01,
          0.0043301270189,
          0.0,
          0.0,
          0.0
        ],
        "Error": 0.0,
        "Adjustment": 0.0,
        "Height": 0.0
      },
      "rtts": {
        "clab-nebula-serf4": 5.895,
        "clab-nebula-serf16": 5.895,
        "clab-nebula-serf19": 13.229,
        "clab-nebula-serf27": 14.309,
        "clab-nebula-serf30": 12.99,
        "clab-nebula-serf1": 10.897,
        "clab-nebula-serf6": 4.33,
        "clab-nebula-serf2": 9.097,
        "clab-nebula-serf10": 4.0,
        "clab-nebula-serf15": 7.399,
        "clab-nebula-serf24": 8.66,
        "clab-nebula-serf21": 10.536,
        "clab-nebula-serf23": 8.888,
        "clab-nebula-serf29": 13.143,
        "clab-nebula-serf8": 8.0,
        "clab-nebula-serf14": 9.097,
        "clab-nebula-serf17": 4.77,
        "clab-nebula-serf28": 13.592,
        "clab-nebula-serf9": 6.0,
        "clab-nebula-serf11": 2.0,
        "clab-nebula-serf5": 4.77,
        "clab-nebula-serf18": 4.33,
        "clab-nebula-serf20": 11.79,
        "clab-nebula-serf25": 16.394,
        "clab-nebula-serf26": 15.256,
        "clab-nebula-serf3": 7.399,
        "clab-nebula-serf7": 10.0,
        "clab-nebula-serf13": 10.897,
        "clab-nebula-serf22": 9.539
      }
    },
    {
      "name": "clab-nebula-serf15",
      "addr": "10.0.2.14",
      "port": 7946,
      "status": "alive",
      "tags": {},
      "coordinate": {
        "Vec": [
          0.004,
          0.0086602540378,
          0.0,
          0.0,
          0.0
        ],
        "Error": 0.0,
        "Adjustment": 0.0,
        "Height": 0.0
      },
      "rtts": {
        "clab-nebula-serf4": 8.888,
        "clab-nebula-serf16": 2.0,
        "clab-nebula-serf19": 5.895,
        "clab-nebula-serf27": 8.66,
        "clab-nebula-serf30": 10.536,
        "clab-nebula-serf1": 9.539,
        "clab-nebula-serf6": 10.536,
        "clab-nebula-serf2": 8.888,
        "clab-nebula-serf10": 4.77,
        "clab-nebula-serf12": 7.399,
        "clab-nebula-serf24": 7.399,
        "clab-nebula-serf21": 4.33,
        "clab-nebula-serf23": 5.895,
        "clab-nebula-serf29": 9.539,
        "clab-nebula-serf8": 4.77,
        "clab-nebula-serf14": 2.0,
        "clab-nebula-serf17": 4.0,
        "clab-nebula-serf28": 8.888,
        "clab-nebula-serf9": 4.33,
        "clab-nebula-serf11": 5.895,
        "clab-nebula-serf5": 9.539,
        "clab-nebula-serf18": 6.0,
        "clab-nebula-serf20": 4.77,
        "clab-nebula-serf25": 9.539,
        "clab-nebula-serf26": 8.888,
        "clab-nebula-serf3": 8.66,
        "clab-nebula-serf7": 5.895,
        "clab-nebula-serf13": 4.0,
        "clab-nebula-serf22": 4.77
      }
    },
    {
      "name": "clab-nebula-serf24",
      "addr": "10.0.3.13",
      "port": 7946,
      "status": "alive",
      "tags": {},
      "coordinate": {
        "Vec": [
          0.01,
          0.012990381056700001,
          0.0,
          0.0,
          0.0
        ],
        "Error": 0.0,
        "Adjustment": 0.0,
        "Height": 0.0
      },
      "rtts": {
        "clab-nebula-serf4": 13.592,
        "clab-nebula-serf16": 5.895,
        "clab-nebula-serf19": 10.0,
        "clab-nebula-serf27": 7.399,
        "clab-nebula-serf30": 4.33,
        "clab-nebula-serf1": 16.394,
        "clab-nebula-serf6": 12.99,
        "clab-nebula-serf2": 15.256,
        "clab-nebula-serf10": 9.539,
        "clab-nebula-serf12": 8.66,
        "clab-nebula-serf15": 7.399,
        "clab-nebula-serf21": 6.0,
        "clab-nebula-serf23": 2.0,
        "clab-nebula-serf29": 4.77,
        "clab-nebula-serf8": 11.79,
        "clab-nebula-serf14": 9.097,
        "clab-nebula-serf17": 4.77,
        "clab-nebula-serf28": 5.895,
        "clab-nebula-serf9": 10.536,
        "clab-nebula-serf11": 8.888,
        "clab-nebula-serf5": 13.143,
        "clab-nebula-serf18": 4.33,
        "clab-nebula-serf20": 8.0,
        "clab-nebula-serf25": 10.897,
        "clab-nebula-serf26": 9.097,
        "clab-nebula-serf3": 14.309,
        "clab-nebula-serf7": 13.229,
        "clab-nebula-serf13": 10.897,
        "clab-nebula-serf22": 4.0
      }
    },
    {
      "name": "clab-nebula-serf21",
      "addr": "10.0.3.10",
      "port": 7946,
      "status": "alive",
      "tags": {},
      "coordinate": {
        "Vec": [
          0.004,
          0.012990381056700001,
          0.0,
          0.0,
          0.0
        ],
        "Error": 0.0,
        "Adjustment": 0.0,
        "Height": 0.0
      },
      "rtts": {
        "clab-nebula-serf4": 13.143,
        "clab-nebula-serf16": 4.77,
        "clab-nebula-serf19": 4.0,
        "clab-nebula-serf27": 4.33,
        "clab-nebula-serf30": 7.399,
        "clab-nebula-serf1": 13.592,
        "clab-nebula-serf6": 14.309,
        "clab-nebula-serf2": 13.143,
        "clab-nebula-serf10": 8.888,
        "clab-nebula-serf12": 10.536,
        "clab-nebula-serf15": 4.33,
        "clab-nebula-serf24": 6.0,
        "clab-nebula-serf23": 4.0,
        "clab-nebula-serf29": 5.895,
        "clab-nebula-serf8": 8.888,
        "clab-nebula-serf14": 4.77,
        "clab-nebula-serf17": 5.895,
        "clab-nebula-serf28": 4.77,
        "clab-nebula-serf9": 8.66,
        "clab-nebula-serf11": 9.539,
        "clab-nebula-serf5": 13.592,
        "clab-nebula-serf18": 7.399,
        "clab-nebula-serf20": 2.0,
        "clab-nebula-serf25": 5.895,
        "clab-nebula-serf26": 4.77,
        "clab-nebula-serf3": 12.99,
        "clab-nebula-serf7": 9.539,
        "clab-nebula-serf13": 5.895,
        "clab-nebula-serf22": 2.0
      }
    },
    {
      "name": "clab-nebula-serf23",
      "addr": "10.0.3.12",
      "port": 7946,
      "status": "alive",
      "tags": {},
      "coordinate": {
        "Vec": [
          0.008,
          0.012990381056700001,
          0.0,
          0.0,
          0.0
        ],
        "Error": 0.0,
        "Adjustment": 0.0,
        "Height": 0.0
      },
      "rtts": {
        "clab-nebula-serf4": 13.143,
        "clab-nebula-serf16": 4.77,
        "clab-nebula-serf19": 8.0,
        "clab-nebula-serf27": 5.895,
        "clab-nebula-serf30": 4.77,
        "clab-nebula-serf1": 15.256,
        "clab-nebula-serf6": 13.143,
        "clab-nebula-serf2": 14.309,
        "clab-nebula-serf10": 8.888,
        "clab-nebula-serf12": 8.888,
        "clab-nebula-serf15": 5.895,
        "clab-nebula-serf24": 2.0,
        "clab-nebula-serf21": 4.0,
        "clab-nebula-serf29": 4.33,
        "clab-nebula-serf8": 10.536,
        "clab-nebula-serf14": 7.399,
        "clab-nebula-serf17": 4.33,
        "clab-nebula-serf28": 4.77,
        "clab-nebula-serf9": 9.539,
        "clab-nebula-serf11": 8.66,
        "clab-nebula-serf5": 12.99,
        "clab-nebula-serf18": 4.77,
        "clab-nebula-serf20": 6.0,
        "clab-nebula-serf25": 9.097,
        "clab-nebula-serf26": 7.399,
        "clab-nebula-serf3": 13.592,
        "clab-nebula-serf7": 11.79,
        "clab-nebula-serf13": 9.097,
        "clab-nebula-serf22": 2.0
      }
    },
    {
      "name": "clab-nebula-serf29",
      "addr": "10.0.3.18",
      "port": 7946,
      "status": "alive",
      "tags": {},
      "coordinate": {
        "Vec": [
          0.008,
          0.0173205080756,
          0.0,
          0.0,
          0.0
        ],
        "Error": 0.0,
        "Adjustment": 0.0,
        "Height": 0.0
      },
      "rtts": {
        "clab-nebula-serf4": 17.436,
        "clab-nebula-serf16": 8.888,
        "clab-nebula-serf19": 9.097,
        "clab-nebula-serf27": 4.0,
        "clab-nebula-serf30": 2.0,
        "clab-nebula-serf1": 19.079,
        "clab-nebula-serf6": 17.436,
        "clab-nebula-serf2": 18.33,
        "clab-nebula-serf10": 13.143,
        "clab-nebula-serf12": 13.143,
        "clab-nebula-serf15": 9.539,
        "clab-nebula-serf24": 4.77,
        "clab-nebula-serf21": 5.895,
        "clab-nebula-serf23": 4.33,
        "clab-nebula-serf8": 14.309,
        "clab-nebula-serf14": 10.536,
        "clab-nebula-serf17": 8.66,
        "clab-nebula-serf28": 2.0,
        "clab-nebula-serf9": 13.592,
        "clab-nebula-serf11": 12.99,
        "clab-nebula-serf5": 17.321,
        "clab-nebula-serf18": 8.888,
        "clab-nebula-serf20": 7.399,
        "clab-nebula-serf25": 8.0,
        "clab-nebula-serf26": 6.0,
        "clab-nebula-serf3": 17.776,
        "clab-nebula-serf7": 15.256,
        "clab-nebula-serf13": 11.79,
        "clab-nebula-serf22": 4.77
      }
    },
    {
      "name": "clab-nebula-serf8",
      "addr": "10.0.1.17",
      "port": 7946,
      "status": "alive",
      "tags": {},
      "coordinate": {
        "Vec": [
          0.002,
          0.0043301270189,
          0.0,
          0.0,
          0.0
        ],
        "Error": 0.0,
        "Adjustment": 0.0,
        "Height": 0.0
      },
      "rtts": {
        "clab-nebula-serf4": 5.895,
        "clab-nebula-serf16": 5.895,
        "clab-nebula-serf19": 8.888,
        "clab-nebula-serf27": 13.143,
        "clab-nebula-serf30": 15.256,
        "clab-nebula-serf1": 4.77,
        "clab-nebula-serf6": 9.097,
        "clab-nebula-serf2": 4.33,
        "clab-nebula-serf10": 4.0,
        "clab-nebula-serf12": 8.0,
        "clab-nebula-serf15": 4.77,
        "clab-nebula-serf24": 11.79,
        "clab-nebula-serf21": 8.888,
        "clab-nebula-serf23": 10.536,
        "clab-nebula-serf29": 14.309,
        "clab-nebula-serf14": 4.33,
        "clab-nebula-serf17": 7.399,
        "clab-nebula-serf28": 13.592,
        "clab-nebula-serf9": 2.0,
        "clab-nebula-serf11": 6.0,
        "clab-nebula-serf5": 7.399,
        "clab-nebula-serf18": 9.097,
        "clab-nebula-serf20": 8.66,
        "clab-nebula-serf25": 13.143,
        "clab-nebula-serf26": 12.99,
        "clab-nebula-serf3": 4.77,
        "clab-nebula-serf7": 2.0,
        "clab-nebula-serf13": 4.77,
        "clab-nebula-serf22": 9.539
      }
    },
    {
      "name": "clab-nebula-serf14",
      "addr": "10.0.2.13",
      "port": 7946,
      "status": "alive",
      "tags": {},
      "coordinate": {
        "Vec": [
          0.002,
          0.0086602540378,
          0.0,
          0.0,
          0.0
        ],
        "Error": 0.0,
        "Adjustment": 0.0,
        "Height": 0.0
      },
      "rtts": {
        "clab-nebula-serf4": 9.539,
        "clab-nebula-serf16": 4.0,
        "clab-nebula-serf19": 4.77,
        "clab-nebula-serf27": 8.888,
        "clab-nebula-serf30": 11.79,
        "clab-nebula-serf1": 8.888,
        "clab-nebula-serf6": 11.79,
        "clab-nebula-serf2": 8.66,
        "clab-nebula-serf10": 5.895,
        "clab-nebula-serf12": 9.097,
        "clab-nebula-serf15": 2.0,
        "clab-nebula-serf24": 9.097,
        "clab-nebula-serf21": 4.77,
        "clab-nebula-serf23": 7.399,
        "clab-nebula-serf29": 10.536,
        "clab-nebula-serf8": 4.33,
        "clab-nebula-serf17": 6.0,
        "clab-nebula-serf28": 9.539,
        "clab-nebula-serf9": 4.77,
        "clab-nebula-serf11": 7.399,
        "clab-nebula-serf5": 10.536,
        "clab-nebula-serf18": 8.0,
        "clab-nebula-serf20": 4.33,
        "clab-nebula-serf25": 8.888,
        "clab-nebula-serf26": 8.66,
        "clab-nebula-serf3": 8.888,
        "clab-nebula-serf7": 4.77,
        "clab-nebula-serf13": 2.0,
        "clab-nebula-serf22": 5.895
      }
    },
    {
      "name": "clab-nebula-serf17",
      "addr": "10.0.2.16",
      "port": 7946,
      "status": "alive",
      "tags": {},
      "coordinate": {
        "Vec": [
          0.008,
          0.0086602540378,
          0.0,
          0.0,
          0.0
        ],
        "Error": 0.0,
        "Adjustment": 0.0,
        "Height": 0.0
      },
      "rtts": {
        "clab-nebula-serf4": 8.888,
        "clab-nebula-serf16": 2.0,
        "clab-nebula-serf19": 9.097,
        "clab-nebula-serf27": 9.539,
        "clab-nebula-serf30": 8.888,
        "clab-nebula-serf1": 11.79,
        "clab-nebula-serf6": 8.888,
        "clab-nebula-serf2": 10.536,
        "clab-nebula-serf10": 4.77,
        "clab-nebula-serf12": 4.77,
        "clab-nebula-serf15": 4.0,
        "clab-nebula-serf24": 4.77,
        "clab-nebula-serf21": 5.895,
        "clab-nebula-serf23": 4.33,
        "clab-nebula-serf29": 8.66,
        "clab-nebula-serf8": 7.399,
        "clab-nebula-serf14": 6.0,
        "clab-nebula-serf28": 8.888,
        "clab-nebula-serf9": 5.895,
        "clab-nebula-serf11": 4.33,
        "clab-nebula-serf5": 8.66,
        "clab-nebula-serf18": 2.0,
        "clab-nebula-serf20": 7.399,
        "clab-nebula-serf25": 11.79,
        "clab-nebula-serf26": 10.536,
        "clab-nebula-serf3": 9.539,
        "clab-nebula-serf7": 9.097,
        "clab-nebula-serf13": 8.0,
        "clab-nebula-serf22": 4.77
      }
    },
    {
      "name": "clab-nebula-serf28",
      "addr": "10.0.3.17",
      "port": 7946,
      "status": "alive",
      "tags": {},
      "coordinate": {
        "Vec": [
          0.006,
          0.0173205080756,
          0.0,
          0.0,
          0.0
        ],
        "Error": 0.0,
        "Adjustment": 0.0,
        "Height": 0.0
      },
      "rtts": {
        "clab-nebula-serf4": 17.321,
        "clab-nebula-serf16": 8.66,
        "clab-nebula-serf19": 7.399,
        "clab-nebula-serf27": 2.0,
        "clab-nebula-serf30": 4.0,
        "clab-nebula-serf1": 18.33,
        "clab-nebula-serf6": 17.776,
        "clab-nebula-serf2": 17.776,
        "clab-nebula-serf10": 12.99,
        "clab-nebula-serf12": 13.592,
        "clab-nebula-serf15": 8.888,
        "clab-nebula-serf24": 5.895,
        "clab-nebula-serf21": 4.77,
        "clab-nebula-serf23": 4.77,
        "clab-nebula-serf29": 2.0,
        "clab-nebula-serf8": 13.592,
        "clab-nebula-serf14": 9.539,
        "clab-nebula-serf17": 8.888,
        "clab-nebula-serf9": 13.143,
        "clab-nebula-serf11": 13.143,
        "clab-nebula-serf5": 17.436,
        "clab-nebula-serf18": 9.539,
        "clab-nebula-serf20": 5.895,
        "clab-nebula-serf25": 6.0,
        "clab-nebula-serf26": 4.0,
        "clab-nebula-serf3": 17.436,
        "clab-nebula-serf7": 14.309,
        "clab-nebula-serf13": 10.536,
        "clab-nebula-serf22": 4.33
      }
    },
    {
      "name": "clab-nebula-serf9",
      "addr": "10.0.1.18",
      "port": 7946,
      "status": "alive",
      "tags": {},
      "coordinate": {
        "Vec": [
          0.004,
          0.0043301270189,
          0.0,
          0.0,
          0.0
        ],
        "Error": 0.0,
        "Adjustment": 0.0,
        "Height": 0.0
      },
      "rtts": {
        "clab-nebula-serf4": 4.77,
        "clab-nebula-serf16": 4.77,
        "clab-nebula-serf19": 9.539,
        "clab-nebula-serf27": 12.99,
        "clab-nebula-serf30": 14.309,
        "clab-nebula-serf1": 5.895,
        "clab-nebula-serf6": 7.399,
        "clab-nebula-serf2": 4.77,
        "clab-nebula-serf10": 2.0,
        "clab-nebula-serf12": 6.0,
        "clab-nebula-serf15": 4.33,
        "clab-nebula-serf24": 10.536,
        "clab-nebula-serf21": 8.66,
        "clab-nebula-serf23": 9.539,
        "clab-nebula-serf29": 13.592,
        "clab-nebula-serf8": 2.0,
        "clab-nebula-serf14": 4.77,
        "clab-nebula-serf17": 5.895,
        "clab-nebula-serf28": 13.143,
        "clab-nebula-serf11": 4.0,
        "clab-nebula-serf5": 5.895,
        "clab-nebula-serf18": 7.399,
        "clab-nebula-serf20": 8.888,
        "clab-nebula-serf25": 13.592,
        "clab-nebula-serf26": 13.143,
        "clab-nebula-serf3": 4.33,
        "clab-nebula-serf7": 4.0,
        "clab-nebula-serf13": 5.895,
        "clab-nebula-serf22": 8.888
      }
    },
    {
      "name": "clab-nebula-serf11",
      "addr": "10.0.2.10",
      "port": 7946,
      "status": "alive",
      "tags": {},
      "coordinate": {
        "Vec": [
          0.008,
          0.0043301270189,
          0.0,
          0.0,
          0.0
        ],
        "Error": 0.0,
        "Adjustment": 0.0,
        "Height": 0.0
      },
      "rtts": {
        "clab-nebula-serf4": 4.77,
        "clab-nebula-serf16": 4.77,
        "clab-nebula-serf19": 11.79,
        "clab-nebula-serf27": 13.592,
        "clab-nebula-serf30": 13.143,
        "clab-nebula-serf1": 9.097,
        "clab-nebula-serf6": 4.77,
        "clab-nebula-serf2": 7.399,
        "clab-nebula-serf10": 2.0,
        "clab-nebula-serf12": 2.0,
        "clab-nebula-serf15": 5.895,
        "clab-nebula-serf24": 8.888,
        "clab-nebula-serf21": 9.539,
        "clab-nebula-serf23": 8.66,
        "clab-nebula-serf29": 12.99,
        "clab-nebula-serf8": 6.0,
        "clab-nebula-serf14": 7.399,
        "clab-nebula-serf17": 4.33,
        "clab-nebula-serf28": 13.143,
        "clab-nebula-serf9": 4.0,
        "clab-nebula-serf5": 4.33,
        "clab-nebula-serf18": 4.77,
        "clab-nebula-serf20": 10.536,
        "clab-nebula-serf25": 15.256,
        "clab-nebula-serf26": 14.309,
        "clab-nebula-serf3": 5.895,
        "clab-nebula-serf7": 8.0,
        "clab-nebula-serf13": 9.097,
        "clab-nebula-serf22": 8.888
      }
    },
    {
      "name": "clab-nebula-serf5",
      "addr": "10.0.1.14",
      "port": 7946,
      "status": "alive",
      "tags": {},
      "coordinate": {
        "Vec": [
          0.008,
          0.0,
          0.0,
          0.0,
          0.0
        ],
        "Error": 0.0,
        "Adjustment": 0.0,
        "Height": 0.0
      },
      "rtts": {
        "clab-nebula-serf4": 2.0,
        "clab-nebula-serf16": 8.888,
        "clab-nebula-serf19": 15.256,
        "clab-nebula-serf27": 17.776,
        "clab-nebula-serf30": 17.436,
        "clab-nebula-serf1": 8.0,
        "clab-nebula-serf6": 2.0,
        "clab-nebula-serf2": 6.0,
        "clab-nebula-serf10": 4.77,
        "clab-nebula-serf12": 4.77,
        "clab-nebula-serf15": 9.539,
        "clab-nebula-serf24": 13.143,
        "clab-nebula-serf21": 13.592,
        "clab-nebula-serf23": 12.99,
        "clab-nebula-serf29": 17.321,
        "clab-nebula-serf8": 7.399,
        "clab-nebula-serf14": 10.536,
        "clab-nebula-serf17": 8.66,
        "clab-nebula-serf28": 17.436,
        "clab-nebula-serf9": 5.895,
        "clab-nebula-serf11": 4.33,
        "clab-nebula-serf18": 8.888,
        "clab-nebula-serf20": 14.309,
        "clab-nebula-serf25": 19.079,
        "clab-nebula-serf26": 18.33,
        "clab-nebula-serf3": 4.0,
        "clab-nebula-serf7": 9.097,
        "clab-nebula-serf13": 11.79,
        "clab-nebula-serf22": 13.143
      }
    },
    {
      "name": "clab-nebula-serf18",
      "addr": "10.0.2.17",
      "port": 7946,
      "status": "alive",
      "tags": {},
      "coordinate": {
        "Vec": [
          0.01,
          0.0086602540378,
          0.0,
          0.0,
          0.0
        ],
        "Error": 0.0,
        "Adjustment": 0.0,
        "Height": 0.0
      },
      "rtts": {
        "clab-nebula-serf4": 9.539,
        "clab-nebula-serf16": 4.0,
        "clab-nebula-serf19": 10.897,
        "clab-nebula-serf27": 10.536,
        "clab-nebula-serf30": 8.66,
        "clab-nebula-serf1": 13.229,
        "clab-nebula-serf6": 8.66,
        "clab-nebula-serf2": 11.79,
        "clab-nebula-serf10": 5.895,
        "clab-nebula-serf12": 4.33,
        "clab-nebula-serf15": 6.0,
        "clab-nebula-serf24": 4.33,
        "clab-nebula-serf21": 7.399,
        "clab-nebula-serf23": 4.77,
        "clab-nebula-serf29": 8.888,
        "clab-nebula-serf8": 9.097,
        "clab-nebula-serf14": 8.0,
        "clab-nebula-serf17": 2.0,
        "clab-nebula-serf28": 9.539,
        "clab-nebula-serf9": 7.399,
        "clab-nebula-serf11": 4.77,
        "clab-nebula-serf5": 8.888,
        "clab-nebula-serf20": 9.097,
        "clab-nebula-serf25": 13.229,
        "clab-nebula-serf26": 11.79,
        "clab-nebula-serf3": 10.536,
        "clab-nebula-serf7": 10.897,
        "clab-nebula-serf13": 10.0,
        "clab-nebula-serf22": 5.895
      }
    },
    {
      "name": "clab-nebula-serf20",
      "addr": "10.0.2.19",
      "port": 7946,
      "status": "alive",
      "tags": {},
      "coordinate": {
        "Vec": [
          0.002,
          0.012990381056700001,
          0.0,
          0.0,
          0.0
        ],
        "Error": 0.0,
        "Adjustment": 0.0,
        "Height": 0.0
      },
      "rtts": {
        "clab-nebula-serf4": 13.592,
        "clab-nebula-serf16": 5.895,
        "clab-nebula-serf19": 2.0,
        "clab-nebula-serf27": 4.77,
        "clab-nebula-serf30": 9.097,
        "clab-nebula-serf1": 13.143,
        "clab-nebula-serf6": 15.256,
        "clab-nebula-serf2": 12.99,
        "clab-nebula-serf10": 9.539,
        "clab-nebula-serf12": 11.79,
        "clab-nebula-serf15": 4.77,
        "clab-nebula-serf24": 8.0,
        "clab-nebula-serf21": 2.0,
        "clab-nebula-serf23": 6.0,
        "clab-nebula-serf29": 7.399,
        "clab-nebula-serf8": 8.66,
        "clab-nebula-serf14": 4.33,
        "clab-nebula-serf17": 7.399,
        "clab-nebula-serf28": 5.895,
        "clab-nebula-serf9": 8.888,
        "clab-nebula-serf11": 10.536,
        "clab-nebula-serf5": 14.309,
        "clab-nebula-serf18": 9.097,
        "clab-nebula-serf25": 4.77,
        "clab-nebula-serf26": 4.33,
        "clab-nebula-serf3": 13.143,
        "clab-nebula-serf7": 8.888,
        "clab-nebula-serf13": 4.77,
        "clab-nebula-serf22": 4.0
      }
    },
    {
      "name": "clab-nebula-serf25",
      "addr": "10.0.3.14",
      "port": 7946,
      "status": "alive",
      "tags": {},
      "coordinate": {
        "Vec": [
          0.0,
          0.0173205080756,
          0.0,
          0.0,
          0.0
        ],
        "Error": 0.0,
        "Adjustment": 0.0,
        "Height": 0.0
      },
      "rtts": {
        "clab-nebula-serf4": 18.33,
        "clab-nebula-serf16": 10.536,
        "clab-nebula-serf19": 4.33,
        "clab-nebula-serf27": 4.0,
        "clab-nebula-serf30": 10.0,
        "clab-nebula-serf1": 17.321,
        "clab-nebula-serf6": 20.0,
        "clab-nebula-serf2": 17.436,
        "clab-nebula-serf10": 14.309,
        "clab-nebula-serf12": 16.394,
        "clab-nebula-serf15": 9.539,
        "clab-nebula-serf24": 10.897,
        "clab-nebula-serf21": 5.895,
        "clab-nebula-serf23": 9.097,
        "clab-nebula-serf29": 8.0,
        "clab-nebula-serf8": 13.143,
        "clab-nebula-serf14": 8.888,
        "clab-nebula-serf17": 11.79,
        "clab-nebula-serf28": 6.0,
        "clab-nebula-serf9": 13.592,
        "clab-nebula-serf11": 15.256,
        "clab-nebula-serf5": 19.079,
        "clab-nebula-serf18": 13.229,
        "clab-nebula-serf20": 4.77,
        "clab-nebula-serf26": 2.0,
        "clab-nebula-serf3": 17.776,
        "clab-nebula-serf7": 12.99,
        "clab-nebula-serf13": 8.66,
        "clab-nebula-serf22": 7.399
      }
    },
    {
      "name": "clab-nebula-serf26",
      "addr": "10.0.3.15",
      "port": 7946,
      "status": "alive",
      "tags": {},
      "coordinate": {
        "Vec": [
          0.002,
          0.0173205080756,
          0.0,
          0.0,
          0.0
        ],
        "Error": 0.0,
        "Adjustment": 0.0,
        "Height": 0.0
      },
      "rtts": {
        "clab-nebula-serf4": 17.776,
        "clab-nebula-serf16": 9.539,
        "clab-nebula-serf19": 4.77,
        "clab-nebula-serf27": 2.0,
        "clab-nebula-serf30": 8.0,
        "clab-nebula-serf1": 17.436,
        "clab-nebula-serf6": 19.079,
        "clab-nebula-serf2": 17.321,
        "clab-nebula-serf10": 13.592,
        "clab-nebula-serf12": 15.256,
        "clab-nebula-serf15": 8.888,
        "clab-nebula-serf24": 9.097,
        "clab-nebula-serf21": 4.77,
        "clab-nebula-serf23": 7.399,
        "clab-nebula-serf29": 6.0,
        "clab-nebula-serf8": 12.99,
        "clab-nebula-serf14": 8.66,
        "clab-nebula-serf17": 10.536,
        "clab-nebula-serf28": 4.0,
        "clab-nebula-serf9": 13.143,
        "clab-nebula-serf11": 14.309,
        "clab-nebula-serf5": 18.33,
        "clab-nebula-serf18": 11.79,
        "clab-nebula-serf20": 4.33,
        "clab-nebula-serf25": 2.0,
        "clab-nebula-serf3": 17.436,
        "clab-nebula-serf7": 13.143,
        "clab-nebula-serf13": 8.888,
        "clab-nebula-serf22": 5.895
      }
    },
    {
      "name": "clab-nebula-serf3",
      "addr": "10.0.1.12",
      "port": 7946,
      "status": "alive",
      "tags": {},
      "coordinate": {
        "Vec": [
          0.004,
          0.0,
          0.0,
          0.0,
          0.0
        ],
        "Error": 0.0,
        "Adjustment": 0.0,
        "Height": 0.0
      },
      "rtts": {
        "clab-nebula-serf4": 2.0,
        "clab-nebula-serf16": 8.888,
        "clab-nebula-serf19": 13.592,
        "clab-nebula-serf27": 17.321,
        "clab-nebula-serf30": 18.33,
        "clab-nebula-serf1": 4.0,
        "clab-nebula-serf6": 6.0,
        "clab-nebula-serf2": 2.0,
        "clab-nebula-serf10": 4.77,
        "clab-nebula-serf12": 7.399,
        "clab-nebula-serf15": 8.66,
        "clab-nebula-serf24": 14.309,
        "clab-nebula-serf21": 12.99,
        "clab-nebula-serf23": 13.592,
        "clab-nebula-serf29": 17.776,
        "clab-nebula-serf8": 4.77,
        "clab-nebula-serf14": 8.888,
        "clab-nebula-serf17": 9.539,
        "clab-nebula-serf28": 17.436,
        "clab-nebula-serf9": 4.33,
        "clab-nebula-serf11": 5.895,
        "clab-nebula-serf5": 4.0,
        "clab-nebula-serf18": 10.536,
        "clab-nebula-serf20": 13.143,
        "clab-nebula-serf25": 17.776,
        "clab-nebula-serf26": 17.436,
        "clab-nebula-serf7": 5.895,
        "clab-nebula-serf13": 9.539,
        "clab-nebula-serf22": 13.143
      }
    },
    {
      "name": "clab-nebula-serf7",
      "addr": "10.0.1.16",
      "port": 7946,
      "status": "alive",
      "tags": {},
      "coordinate": {
        "Vec": [
          0.0,
          0.0043301270189,
          0.0,
          0.0,
          0.0
        ],
        "Error": 0.0,
        "Adjustment": 0.0,
        "Height": 0.0
      },
      "rtts": {
        "clab-nebula-serf4": 7.399,
        "clab-nebula-serf16": 7.399,
        "clab-nebula-serf19": 8.66,
        "clab-nebula-serf27": 13.592,
        "clab-nebula-serf30": 16.394,
        "clab-nebula-serf1": 4.33,
        "clab-nebula-serf6": 10.897,
        "clab-nebula-serf2": 4.77,
        "clab-nebula-serf10": 6.0,
        "clab-nebula-serf12": 10.0,
        "clab-nebula-serf15": 5.895,
        "clab-nebula-serf24": 13.229,
        "clab-nebula-serf21": 9.539,
        "clab-nebula-serf23": 11.79,
        "clab-nebula-serf29": 15.256,
        "clab-nebula-serf8": 2.0,
        "clab-nebula-serf14": 4.77,
        "clab-nebula-serf17": 9.097,
        "clab-nebula-serf28": 14.309,
        "clab-nebula-serf9": 4.0,
        "clab-nebula-serf11": 8.0,
        "clab-nebula-serf5": 9.097,
        "clab-nebula-serf18": 10.897,
        "clab-nebula-serf20": 8.888,
        "clab-nebula-serf25": 12.99,
        "clab-nebula-serf26": 13.143,
        "clab-nebula-serf3": 5.895,
        "clab-nebula-serf13": 4.33,
        "clab-nebula-serf22": 10.536
      }
    },
    {
      "name": "clab-nebula-serf13",
      "addr": "10.0.2.12",
      "port": 7946,
      "status": "alive",
      "tags": {},
      "coordinate": {
        "Vec": [
          0.0,
          0.0086602540378,
          0.0,
          0.0,
          0.0
        ],
        "Error": 0.0,
        "Adjustment": 0.0,
        "Height": 0.0
      },
      "rtts": {
        "clab-nebula-serf4": 10.536,
        "clab-nebula-serf16": 6.0,
        "clab-nebula-serf19": 4.33,
        "clab-nebula-serf27": 9.539,
        "clab-nebula-serf30": 13.229,
        "clab-nebula-serf1": 8.66,
        "clab-nebula-serf6": 13.229,
        "clab-nebula-serf2": 8.888,
        "clab-nebula-serf10": 7.399,
        "clab-nebula-serf12": 10.897,
        "clab-nebula-serf15": 4.0,
        "clab-nebula-serf24": 10.897,
        "clab-nebula-serf21": 5.895,
        "clab-nebula-serf23": 9.097,
        "clab-nebula-serf29": 11.79,
        "clab-nebula-serf8": 4.77,
        "clab-nebula-serf14": 2.0,
        "clab-nebula-serf17": 8.0,
        "clab-nebula-serf28": 10.536,
        "clab-nebula-serf9": 5.895,
        "clab-nebula-serf11": 9.097,
        "clab-nebula-serf5": 11.79,
        "clab-nebula-serf18": 10.0,
        "clab-nebula-serf20": 4.77,
        "clab-nebula-serf25": 8.66,
        "clab-nebula-serf26": 8.888,
        "clab-nebula-serf3": 9.539,
        "clab-nebula-serf7": 4.33,
        "clab-nebula-serf22": 7.399
      }
    },
    {
      "name": "clab-nebula-serf22",
      "addr": "10.0.3.11",
      "port": 7946,
      "status": "alive",
      "tags": {},
      "coordinate": {
        "Vec": [
          0.006,
          0.012990381056700001,
          0.0,
          0.0,
          0.0
        ],
        "Error": 0.0,
        "Adjustment": 0.0,
        "Height": 0.0
      },
      "rtts": {
        "clab-nebula-serf4": 12.99,
        "clab-nebula-serf16": 4.33,
        "clab-nebula-serf19": 6.0,
        "clab-nebula-serf27": 4.77,
        "clab-nebula-serf30": 5.895,
        "clab-nebula-serf1": 14.309,
        "clab-nebula-serf6": 13.592,
        "clab-nebula-serf2": 13.592,
        "clab-nebula-serf10": 8.66,
        "clab-nebula-serf12": 9.539,
        "clab-nebula-serf15": 4.77,
        "clab-nebula-serf24": 4.0,
        "clab-nebula-serf21": 2.0,
        "clab-nebula-serf23": 2.0,
        "clab-nebula-serf29": 4.77,
        "clab-nebula-serf8": 9.539,
        "clab-nebula-serf14": 5.895,
        "clab-nebula-serf17": 4.77,
        "clab-nebula-serf28": 4.33,
        "clab-nebula-serf9": 8.888,
        "clab-nebula-serf11": 8.888,
        "clab-nebula-serf5": 13.143,
        "clab-nebula-serf18": 5.895,
        "clab-nebula-serf20": 4.0,
        "clab-nebula-serf25": 7.399,
        "clab-nebula-serf26": 5.895,
        "clab-nebula-serf3": 13.143,
        "clab-nebula-serf7": 10.536,
        "clab-nebula-serf13": 7.399
      }
    }
  ]
}